glory/__init__.py
glory/model.py
glory/data/__init__.py
glory/data/read_config.py
glory/data/read_data.py
glory/data/write_outputs.py
glory/method/__init__.py
glory/method/lp.py
glory/method/supply_curve.py
glory/utils/__init__.py
glory/utils/cleanup.py
glory/utils/diagnostics.py
glory/utils/install_supplement.py
glory/utils/logger.py
glory_reservoir-0.1.0.dist-info/METADATA
glory_reservoir-0.1.0.dist-info/WHEEL
glory_reservoir-0.1.0.dist-info/licenses/LICENSE
glory_reservoir-0.1.0.dist-info/RECORD
