Metadata-Version: 2.3
Name: glory-reservoir
Version: 0.1.0
Summary: A python package for estimating global reservoir yield and costs for water supply.
Project-URL: Repository, https://github.com/JGCRI/glory
Project-URL: Documentation, https://jgcri.github.io/glory
Author-email: Mengqi Zhao <mengqi.zhao@pnnl.gov>
Maintainer-email: Mengqi Zhao <mengqi.zhao@pnnl.gov>
License: GLORY
License-File: LICENSE
Classifier: Development Status :: 4 - Beta
Classifier: Programming Language :: Python :: 3.9
Classifier: Programming Language :: Python :: 3.10
Classifier: Programming Language :: Python :: 3.11
Requires-Python: >=3.9
Requires-Dist: matplotlib>=3.7.2
Requires-Dist: numpy<2,>=1.23
Requires-Dist: pandas>=1.5
Requires-Dist: pyomo>=6.6.2
Requires-Dist: pyyaml>=5.4.1
Requires-Dist: requests>=2.25.1
Requires-Dist: scipy>=1.11.2
Requires-Dist: toml>=0.10.2
Provides-Extra: deploy
Requires-Dist: twine>=4.0.1; extra == 'deploy'
Provides-Extra: docs
Requires-Dist: autodoc>=0.5.0; extra == 'docs'
Requires-Dist: ipykernel>=6.15.1; extra == 'docs'
Requires-Dist: nbsphinx~=0.8.6; extra == 'docs'
Requires-Dist: sphinx-design~=0.5.0; extra == 'docs'
Requires-Dist: sphinx-mathjax-offline~=0.0.2; extra == 'docs'
Requires-Dist: sphinx-rtd-theme~=2.0.0; extra == 'docs'
Requires-Dist: sphinx~=7.2.6; extra == 'docs'
Provides-Extra: test
Requires-Dist: pytest>=6.0; extra == 'test'
